novalabs/__init__.py
novalabs/clients/__init__.py
novalabs/clients/binance.py
novalabs/clients/bybit.py
novalabs/clients/clients.py
novalabs/clients/kucoin.py
novalabs/clients/oanda.py
novalabs/clients/okx.py
novalabs/data/__init__.py
novalabs/data/discord.py
novalabs/data/reddit.py
novalabs/data/telegram.py
novalabs/interfaces/backtest_interface.py
novalabs/interfaces/client_interface.py
novalabs/interfaces/indicator_interface.py
novalabs/strategies/__init__.py
novalabs/strategies/macd_strategy.py
novalabs/strategies/random_strategy.py
novalabs/utils/__init__.py
novalabs/utils/backtest.py
novalabs/utils/constant.py
novalabs/utils/helpers.py
novalabs/utils/indicators.py
tests/__init__.py
tests/backtest/__init__.py
tests/backtest/test_all_pairs_real_positions.py
tests/backtest/test_fast_download_history.py
tests/backtest/test_get_historical_data.py
tests/backtest/test_run_backtest.py
tests/clients/__init__.py
tests/clients/test_format_data.py
tests/clients/test_get_candles.py
tests/clients/test_get_earliest_timestamp.py
tests/clients/test_get_historical_data.py
tests/clients/test_get_most_traded_pairs.py
tests/clients/test_get_pairs_info.py
tests/clients/test_get_server_time.py
tests/indicators/__init__.py
novalabs_backtest-1.1.27.dist-info/LICENSE
novalabs_backtest-1.1.27.dist-info/METADATA
novalabs_backtest-1.1.27.dist-info/WHEEL
novalabs_backtest-1.1.27.dist-info/top_level.txt
novalabs_backtest-1.1.27.dist-info/RECORD
